browsercookie/__init__.py
browsercookie-0.8.2.dist-info/licenses/LICENSE.txt
browsercookie-0.8.2.dist-info/METADATA
browsercookie-0.8.2.dist-info/WHEEL
browsercookie-0.8.2.dist-info/top_level.txt
browsercookie-0.8.2.dist-info/RECORD
