Metadata-Version: 2.4
Name: browsercookie
Version: 0.8.2
Summary: Loads cookies from your browser into a cookiejar object so can download with urllib and other libraries the same content you see in the web browser.
Home-page: https://github.com/richardpenman/browsercookie
Author: Richard Penman
Author-email: richard.penman@gmail.com
License: lgpl
Requires-Python: >=3.4
License-File: LICENSE.txt
Requires-Dist: cryptography
Requires-Dist: keyring
Requires-Dist: lz4
Requires-Dist: pywin32; sys_platform == "win32"
Dynamic: author
Dynamic: author-email
Dynamic: description
Dynamic: description-content-type
Dynamic: home-page
Dynamic: license
Dynamic: license-file
Dynamic: requires-dist
Dynamic: requires-python
Dynamic: summary
